BackboneJsZhongwenWendang112/README.md
BackboneJsZhongwenWendang112/__init__.py
BackboneJsZhongwenWendang112/__main__.py
BackboneJsZhongwenWendang112/file.epub
BackboneJsZhongwenWendang112/index.html
BackboneJsZhongwenWendang112/css/__init__.py
BackboneJsZhongwenWendang112/css/annotations.css
BackboneJsZhongwenWendang112/css/main.css
BackboneJsZhongwenWendang112/css/normalize.css
BackboneJsZhongwenWendang112/css/popup.css
BackboneJsZhongwenWendang112/font/__init__.py
BackboneJsZhongwenWendang112/font/fontello.eot
BackboneJsZhongwenWendang112/font/fontello.svg
BackboneJsZhongwenWendang112/font/fontello.ttf
BackboneJsZhongwenWendang112/font/fontello.woff
BackboneJsZhongwenWendang112/img/__init__.py
BackboneJsZhongwenWendang112/img/annotator-glyph-sprite.png
BackboneJsZhongwenWendang112/img/annotator-icon-sprite.png
BackboneJsZhongwenWendang112/img/apple-touch-icon.png
BackboneJsZhongwenWendang112/img/cancelfullscreen.png
BackboneJsZhongwenWendang112/img/close.png
BackboneJsZhongwenWendang112/img/fullscreen.png
BackboneJsZhongwenWendang112/img/loader.gif
BackboneJsZhongwenWendang112/img/menu-icon.png
BackboneJsZhongwenWendang112/img/save.png
BackboneJsZhongwenWendang112/img/saved.png
BackboneJsZhongwenWendang112/img/settings-s.png
BackboneJsZhongwenWendang112/img/settings.png
BackboneJsZhongwenWendang112/img/star.png
BackboneJsZhongwenWendang112/js/__init__.py
BackboneJsZhongwenWendang112/js/epub.js
BackboneJsZhongwenWendang112/js/epub.min.js
BackboneJsZhongwenWendang112/js/epub.min.map
BackboneJsZhongwenWendang112/js/hooks.min.js
BackboneJsZhongwenWendang112/js/hooks.min.map
BackboneJsZhongwenWendang112/js/reader.js
BackboneJsZhongwenWendang112/js/reader.js.map
BackboneJsZhongwenWendang112/js/reader.min.js
BackboneJsZhongwenWendang112/js/reader.min.map
BackboneJsZhongwenWendang112/js/hooks/__init__.py
BackboneJsZhongwenWendang112/js/hooks/extensions/__init__.py
BackboneJsZhongwenWendang112/js/hooks/extensions/highlight.js
backbone_js_zhongwen_wendang_1_1_2-2024.3.1.0.dist-info/METADATA
backbone_js_zhongwen_wendang_1_1_2-2024.3.1.0.dist-info/WHEEL
backbone_js_zhongwen_wendang_1_1_2-2024.3.1.0.dist-info/entry_points.txt
backbone_js_zhongwen_wendang_1_1_2-2024.3.1.0.dist-info/top_level.txt
backbone_js_zhongwen_wendang_1_1_2-2024.3.1.0.dist-info/RECORD
